toolmate_sdk/README.md
toolmate_sdk/__init__.py
toolmate_sdk/requirements.txt
toolmate_sdk/backends/anthropic.py
toolmate_sdk/backends/azure.py
toolmate_sdk/backends/custom.py
toolmate_sdk/backends/deepseek.py
toolmate_sdk/backends/genai.py
toolmate_sdk/backends/github.py
toolmate_sdk/backends/googleai.py
toolmate_sdk/backends/groq.py
toolmate_sdk/backends/llamacpp.py
toolmate_sdk/backends/mistral.py
toolmate_sdk/backends/ollama.py
toolmate_sdk/backends/openai.py
toolmate_sdk/backends/xai.py
toolmate_sdk/contexts/README.md
toolmate_sdk/contexts/reflect.md
toolmate_sdk/contexts/think.md
toolmate_sdk/plugins/README.md
toolmate_sdk/prompts/README.md
toolmate_sdk/prompts/refine.md
toolmate_sdk/prompts/review.md
toolmate_sdk/systems/README.md
toolmate_sdk/systems/assign_agents.md
toolmate_sdk/systems/create_agents.md
toolmate_sdk/systems/write_final_answer.md
toolmate_sdk/tools/README.md
toolmate_sdk/tools/search_google.py
toolmate_sdk/tools/send_gmail.py
toolmate_sdk/tools/send_outlook.py
toolmate_sdk/tools/task.py
toolmate_sdk/utils/handle_python_code.py
toolmate_sdk/utils/handle_text.py
toolmate_sdk/utils/instructions.py
toolmate_sdk/utils/manage_package.py
toolmate_sdk/utils/online.py
toolmate_sdk/utils/retrieve_text_output.py
toolmate_sdk/utils/schema.py
toolmate_sdk/utils/system.py
toolmate_sdk/utils/text_wrapper.py
toolmate_sdk-0.0.16.dist-info/LICENSE
toolmate_sdk-0.0.16.dist-info/METADATA
toolmate_sdk-0.0.16.dist-info/WHEEL
toolmate_sdk-0.0.16.dist-info/top_level.txt
toolmate_sdk-0.0.16.dist-info/RECORD
