Metadata-Version: 2.2
Name: toolmate-sdk
Version: 0.0.16
Summary: ToolMate-SDK: a software developement kit for developing agentic AI applications that support 13 LLM backends and integrate tools and agents. (Developer: Eliran Wong)
Home-page: https://github.com/eliranwong/toolmate-sdk
Author: Eliran Wong
Author-email: support@toolmate.ai
License: GNU General Public License (GPL)
Project-URL: Source, https://github.com/eliranwong/toolmate-sdk
Project-URL: Tracker, https://github.com/eliranwong/toolmate-sdk/issues
Project-URL: Documentation, https://github.com/eliranwong/toolmate-sdk/wiki
Project-URL: Funding, https://www.paypal.me/toolmate
Keywords: toolmate ai sdk anthropic azure chatgpt deepseek genai github googleai groq llamacpp mistral ollama openai vertexai xai
Classifier: Development Status :: 5 - Production/Stable
Classifier: Intended Audience :: End Users/Desktop
Classifier: Topic :: Utilities
Classifier: Topic :: Scientific/Engineering :: Artificial Intelligence
Classifier: Topic :: Software Development :: Build Tools
Classifier: License :: OSI Approved :: GNU General Public License v3 or later (GPLv3+)
Classifier: Programming Language :: Python :: 3.8
Classifier: Programming Language :: Python :: 3.9
Classifier: Programming Language :: Python :: 3.10
Classifier: Programming Language :: Python :: 3.11
Classifier: Programming Language :: Python :: 3.12
Requires-Python: >=3.8, <3.13
License-File: LICENSE
Requires-Dist: ollama>=0.4.7
Requires-Dist: groq>=0.15.0
Requires-Dist: mistralai>=1.5.0
Requires-Dist: openai>=1.60.2
Requires-Dist: tiktoken>=0.8.0
Requires-Dist: anthropic>=0.45.2
Requires-Dist: prompt_toolkit
Requires-Dist: packaging
Requires-Dist: importlib_metadata
Provides-Extra: genai
Requires-Dist: google-genai>=0.6.0; extra == "genai"
Dynamic: author
Dynamic: author-email
Dynamic: classifier
Dynamic: description
Dynamic: home-page
Dynamic: keywords
Dynamic: license
Dynamic: project-url
Dynamic: provides-extra
Dynamic: requires-dist
Dynamic: requires-python
Dynamic: summary
